koya_python_airtable/__init__.py
koya_python_airtable/koya_python_airtable.py
koya_python_airtable-0.0.7.dist-info/LICENSE
koya_python_airtable-0.0.7.dist-info/METADATA
koya_python_airtable-0.0.7.dist-info/WHEEL
koya_python_airtable-0.0.7.dist-info/top_level.txt
koya_python_airtable-0.0.7.dist-info/RECORD
