Metadata-Version: 2.1
Name: koya-python-airtable
Version: 0.0.7
Author: 
Author-email: 
License: MIT
Requires-Python: >=3.6
License-File: LICENSE
Requires-Dist: pandas
Requires-Dist: requests
